README.txt
setup.py
Products/__init__.py
Products.DocFinderTab.egg-info/PKG-INFO
Products.DocFinderTab.egg-info/SOURCES.txt
Products.DocFinderTab.egg-info/dependency_links.txt
Products.DocFinderTab.egg-info/namespace_packages.txt
Products.DocFinderTab.egg-info/not-zip-safe
Products.DocFinderTab.egg-info/requires.txt
Products.DocFinderTab.egg-info/top_level.txt
Products/DocFinderTab/CHANGES.txt
Products/DocFinderTab/README.txt
Products/DocFinderTab/__init__.py
Products/DocFinderTab/analyse.py
Products/DocFinderTab/config.py
Products/DocFinderTab/patch_inspect.py
Products/DocFinderTab/patch_zope.py
Products/DocFinderTab/permissions.py
Products/DocFinderTab/version.txt
Products/DocFinderTab/dtml/showDocumentation.dtml
Products/DocFinderTab/help/README.stx
Products/DocFinderTab/tests/__init__.py
Products/DocFinderTab/tests/testAnalyse.py
Products/DocFinderTab/tests/testDocFinderTab.py