Metadata-Version: 1.0
Name: Products.DocFinderTab
Version: 1.0.5
Summary: Makes Dieter Maurer's DocFinder available from a ZMI management tab
Home-page: http://plone.org/products/docfindertab
Author: Stefan H. Holek
Author-email: stefan@epy.co.at
License: ZPL
Keywords: Zope2 DocFinder DocFinderTab
Platform: UNKNOWN
Classifier: Programming Language :: Python
Classifier: Topic :: Software Development :: Libraries :: Python Modules
Classifier: Framework :: Zope2
Classifier: Framework :: Plone
